troubleshooter/__init__.py
troubleshooter/log.py
troubleshooter/version.py
troubleshooter/common/__init__.py
troubleshooter/common/format_msg.py
troubleshooter/common/framework_detection.py
troubleshooter/common/ms_callback.py
troubleshooter/common/ms_utils.py
troubleshooter/common/util.py
troubleshooter/migrator/__init__.py
troubleshooter/migrator/diff_handler.py
troubleshooter/migrator/net_diff_finder.py
troubleshooter/migrator/save.py
troubleshooter/migrator/weight_migrator.py
troubleshooter/migrator/api_dump/__init__.py
troubleshooter/migrator/api_dump/api_dump_compare.py
troubleshooter/migrator/api_dump/universal_interface.py
troubleshooter/migrator/api_dump/ad_dump/__init__.py
troubleshooter/migrator/api_dump/ad_dump/hook_module.py
troubleshooter/migrator/api_dump/ad_dump/hooks.py
troubleshooter/migrator/api_dump/ad_dump/initialize.py
troubleshooter/migrator/api_dump/ad_dump/support_wrap_ops.yaml
troubleshooter/migrator/api_dump/ad_dump/wrap_functional.py
troubleshooter/migrator/api_dump/ad_dump/wrap_nn.py
troubleshooter/migrator/api_dump/ad_dump/wrap_tensor.py
troubleshooter/migrator/api_dump/ad_dump/wrap_torch.py
troubleshooter/migrator/api_dump/apis_match/__init__.py
troubleshooter/migrator/api_dump/apis_match/api_io_dict.py
troubleshooter/migrator/api_dump/apis_match/api_name_dict.py
troubleshooter/migrator/api_dump/apis_match/apis_match.py
troubleshooter/migrator/api_dump/ms_dump/__init__.py
troubleshooter/migrator/api_dump/ms_dump/hook_cell.py
troubleshooter/migrator/api_dump/ms_dump/hooks.py
troubleshooter/migrator/api_dump/ms_dump/initialize.py
troubleshooter/migrator/api_dump/ms_dump/support_wrap_ops.yaml
troubleshooter/migrator/api_dump/ms_dump/utils.py
troubleshooter/migrator/api_dump/ms_dump/wrap_functional.py
troubleshooter/migrator/api_dump/ms_dump/wrap_nn.py
troubleshooter/migrator/api_dump/ms_dump/wrap_sub_tensor.py
troubleshooter/migrator/api_dump/ms_dump/wrap_tensor.py
troubleshooter/migrator/api_dump/pt_dump/__init__.py
troubleshooter-1.0.18.dist-info/LICENSE
troubleshooter-1.0.18.dist-info/METADATA
troubleshooter-1.0.18.dist-info/WHEEL
troubleshooter-1.0.18.dist-info/top_level.txt
troubleshooter-1.0.18.dist-info/RECORD
